altspell/__init__.py
altspell/containers.py
altspell/exceptions.py
altspell/model.py
altspell/repositories.py
altspell/services.py
altspell/blueprints/__init__.py
altspell/blueprints/spelling_system.py
altspell/blueprints/translation.py
altspell/utils/hcaptcha.py
altspell/utils/populate_spelling_system_table.py
altspell-0.4.0.dist-info/WHEEL
altspell-0.4.0.dist-info/METADATA
altspell-0.4.0.dist-info/RECORD
