Metadata-Version: 2.4
Name: altspell
Version: 0.4.0
Summary: A flask web API for translating between traditional English spellings and alternative spellings
Author-email: Nicholas Johnson <njohnson@posteo.net>
Requires-Python: >=3.8,<4
Classifier: Development Status :: 3 - Alpha
Classifier: Intended Audience :: Developers
Classifier: Programming Language :: Python
Classifier: License :: OSI Approved :: GNU General Public License v3 or later (GPLv3+)
Classifier: Operating System :: OS Independent
Requires-Dist: altspell_plugins==0.2.2
Requires-Dist: dependency_injector==4.46.0
Requires-Dist: flask==3.1.0
Requires-Dist: flask_sqlalchemy==3.1.1
Requires-Dist: flask_cors==5.0.1
Requires-Dist: flask_caching==2.3.1
Requires-Dist: flask_migrate==4.1.0
Requires-Dist: psycopg2==2.9.10
Requires-Dist: pytz==2025.2
Requires-Dist: requests==2.32.3
